odoo/addons/web_switch_context_warning/README.rst
odoo/addons/web_switch_context_warning/__init__.py
odoo/addons/web_switch_context_warning/__manifest__.py
odoo/addons/web_switch_context_warning/i18n/ca.po
odoo/addons/web_switch_context_warning/i18n/es.po
odoo/addons/web_switch_context_warning/i18n/fr.po
odoo/addons/web_switch_context_warning/i18n/pt_BR.po
odoo/addons/web_switch_context_warning/i18n/web_switch_company_warning.pot
odoo/addons/web_switch_context_warning/i18n/web_switch_context_warning.pot
odoo/addons/web_switch_context_warning/i18n/zh_CN.po
odoo/addons/web_switch_context_warning/readme/CONTRIBUTORS.rst
odoo/addons/web_switch_context_warning/readme/DESCRIPTION.rst
odoo/addons/web_switch_context_warning/readme/ROADMAP.rst
odoo/addons/web_switch_context_warning/readme/USAGE.rst
odoo/addons/web_switch_context_warning/static/description/icon.png
odoo/addons/web_switch_context_warning/static/description/index.html
odoo/addons/web_switch_context_warning/static/src/js/switch_context_warning.js
odoo/addons/web_switch_context_warning/static/src/js/switch_context_warning_worker.js
odoo/addons/web_switch_context_warning/static/src/xml/switch_context_warning.xml
odoo/addons/web_switch_context_warning/view/view.xml
odoo12_addon_web_switch_context_warning-12.0.2.0.0.99.dev16.dist-info/METADATA
odoo12_addon_web_switch_context_warning-12.0.2.0.0.99.dev16.dist-info/WHEEL
odoo12_addon_web_switch_context_warning-12.0.2.0.0.99.dev16.dist-info/top_level.txt
odoo12_addon_web_switch_context_warning-12.0.2.0.0.99.dev16.dist-info/RECORD
