Metadata-Version: 2.1
Name: odoo12-addon-web-switch-context-warning
Version: 12.0.2.0.0.99.dev16
Summary: Show a warning if current user, company or database have been switched in another tab or window.
Home-page: https://github.com/OCA/web
Author: Akretion, Odoo Community Association (OCA)
Author-email: support@odoo-community.org
License: AGPL-3
Platform: UNKNOWN
Classifier: Programming Language :: Python
Classifier: Framework :: Odoo
Classifier: Framework :: Odoo :: 12.0
Classifier: License :: OSI Approved :: GNU Affero General Public License v3
Requires-Python: >=3.5
Requires-Dist: odoo <12.1dev,>=12.0a
